wowool/apps/topics/__init__.py
wowool/apps/topics/config.py
wowool/tools/topic_identifier/__init__.py
wowool/tools/topic_identifier/__main__.py
wowool/tools/topic_identifier/argument_parser.py
wowool/tools/topic_identifier/compiler/__init__.py
wowool/tools/topic_identifier/compiler/__main__.py
wowool/topic_identifier/__init__.py
wowool/topic_identifier/app_id.py
wowool/topic_identifier/config.py
wowool/topic_identifier/topic_identifier.py
wowool/topic_identifier/compiler/__init__.py
wowool/topic_identifier/compiler/compiler.py
wowool_topic_identifier-3.1.3.dist-info/METADATA
wowool_topic_identifier-3.1.3.dist-info/WHEEL
wowool_topic_identifier-3.1.3.dist-info/entry_points.txt
wowool_topic_identifier-3.1.3.dist-info/top_level.txt
wowool_topic_identifier-3.1.3.dist-info/RECORD
