Metadata-Version: 2.4
Name: wowool-topic-identifier
Version: 3.1.3
Summary: Wowool NLP Toolkit Topic Identifier
Author: Wowool
Requires-Python: >=3.11
Requires-Dist: wowool-sdk
Requires-Dist: rich
Dynamic: author
Dynamic: description
Dynamic: description-content-type
Dynamic: requires-dist
Dynamic: requires-python
Dynamic: summary
